neolibrary/__init__.py
neolibrary/config/config.py
neolibrary/decorators.py
neolibrary/monitoring/__init__.py
neolibrary/monitoring/config/config.py
neolibrary/monitoring/logger.py
neolibrary/preproc.py
neolibrary/thumbnail_creator.py
neolibrary/utils.py
neolibrary-0.4.6b1.dist-info/LICENSE
neolibrary-0.4.6b1.dist-info/METADATA
neolibrary-0.4.6b1.dist-info/WHEEL
neolibrary-0.4.6b1.dist-info/RECORD
