Metadata-Version: 2.1
Name: neolibrary
Version: 0.4.6b1
Summary: The general utils library for neomedsys development
License: Apache-2.0 license
Author: Martin Soria Røvang
Author-email: martinrovang@gmail.com
Requires-Python: >=3.9,<4.0
Classifier: License :: Other/Proprietary License
Classifier: Programming Language :: Python :: 3
Classifier: Programming Language :: Python :: 3.9
Classifier: Programming Language :: Python :: 3.10
Classifier: Programming Language :: Python :: 3.11
Requires-Dist: arrow (>=1.2.3,<2.0.0)
Requires-Dist: blosc (>=1.11.1,<2.0.0)
Requires-Dist: colorlog (>=6.7.0,<7.0.0)
Requires-Dist: nibabel (>=5.1.0,<6.0.0)
Requires-Dist: numpy (>=1.25.2,<2.0.0)
Requires-Dist: scikit-image (>=0.22.0,<0.23.0)
Requires-Dist: simpleitk (>=2.0.0,<3.0.0)
